spakky/event/__init__.py
spakky/event/error.py
spakky/event/event_consumer.py
spakky/event/event_publisher.py
spakky/event/stereotype/__init__.py
spakky/event/stereotype/event_handler.py
spakky_event-5.0.1.dist-info/WHEEL
spakky_event-5.0.1.dist-info/METADATA
spakky_event-5.0.1.dist-info/RECORD
