Metadata-Version: 2.3
Name: spakky-event
Version: 5.0.1
Summary: Event handling stereotype for Spakky Framework (@EventHandler, @on_event)
Author: Spakky
Author-email: Spakky <sejong418@icloud.com>
Requires-Dist: spakky-domain>=5.0.1
Requires-Python: >=3.11
